isntall/__init__.py
isntall-1.0.1.dist-info/licenses/LICENSE.txt
isntall-1.0.1.dist-info/METADATA
isntall-1.0.1.dist-info/WHEEL
isntall-1.0.1.dist-info/top_level.txt
isntall-1.0.1.dist-info/RECORD
